demo/__init__.py
demo/test.py
malama_cores-0.2.dist-info/DESCRIPTION.rst
malama_cores-0.2.dist-info/METADATA
malama_cores-0.2.dist-info/RECORD
malama_cores-0.2.dist-info/WHEEL
malama_cores-0.2.dist-info/metadata.json
malama_cores-0.2.dist-info/top_level.txt
