Metadata-Version: 2.0
Name: malama-cores
Version: 0.2
Summary: Core libraries for malama
Home-page: UNKNOWN
Author: andy zhang
Author-email: UNKNOWN
License: BSD
Platform: UNKNOWN
Classifier: Development Status :: 1 - Planning
